antispaminc/__init__.py
antispaminc/class_types.py
antispaminc/connect.py
antispaminc-4.0.dist-info/LICENSE
antispaminc-4.0.dist-info/METADATA
antispaminc-4.0.dist-info/WHEEL
antispaminc-4.0.dist-info/top_level.txt
antispaminc-4.0.dist-info/RECORD
