Metadata-Version: 2.1
Name: antispaminc
Version: 4.0
Summary: A Python Wrapper For Antispam Inc.
Home-page: http://antispaminc.tk
Author: Leo
Author-email: dev@antispaminc.tk
License: License :: OSI Approved :: GNU Lesser General Public License v3 (LGPLv3)
Platform: UNKNOWN
Classifier: Programming Language :: Python :: 3
Classifier: Operating System :: OS Independent
Requires-Python: >=3.6
Requires-Dist: requests (>=2.22.0)
